ass02/adder.v
module adder(a,b,c,sum,cout);
  input a,b,c;
  output sum,cout;
  assign sum=a^b^c;
  assign cout=(a&b)|(a^b)&c;
endmodule

ass02/test_adder.v
module test_adder;
  reg a,b,c;
  wire sum,cout;
  adder a1(a,b,c,sum,cout);
  initial
  begin
	  $dumpfile("dump.vcd");
	  $dumpvars;
	  $display($time,"|a|b|c|sum|cout");
	  $monitor($time,"|%b|%b|%b|%b  |%b",a,b,c,sum,cout);
	  a=0; b=0; c=0;
	  #10 a=0; b=0; c=1;
	  #10 a=0; b=1; c=0;
	  #10 a=0; b=1; c=1;
	  #10 a=1; b=0; c=0;
	  #10 a=1; b=0; c=1;
	  #10 a=1; b=1; c=0;
	  #10 a=1; b=1; c=1;
	  $finish;
  end
endmodule

ass02/dump.vcd
$date
	Tue Aug 09 20:20:16 2022
$end
$version
	Icarus Verilog
$end
$timescale
	1s
$end
$scope module test_adder $end
$var wire 1 ! sum $end
$var wire 1 " cout $end
$var reg 1 # a $end
$var reg 1 $ b $end
$var reg 1 % c $end
$scope module a1 $end
$var wire 1 # a $end
$var wire 1 $ b $end
$var wire 1 % c $end
$var wire 1 " cout $end
$var wire 1 ! sum $end
$upscope $end
$upscope $end
$enddefinitions $end
#0
$dumpvars
0%
0$
0#
0"
0!
$end
#10
1!
1%
#20
0%
1$
#30
1"
0!
1%
#40
0"
1!
0%
0$
1#
#50
1"
0!
1%
#60
0%
1$
#70
1!
1%
